{"0": {"status": "active", "trace": [{"name": "main", "args": ["3cb2fd26e550c2210a94d899a48ecd53216457e9c33f4a623bb3bb63263062a8.exe"], "addr": 4569496, "ret": "symbolic", "addr_func": 4569496}, {"name": "GetVersion", "args": [], "addr_func": "5242896", "addr": 4569534, "ret": 0}, {"name": "HeapCreate", "args": [0, 4096, 0], "addr_func": "5242988", "addr": 4572705, "ret": 1}, {"name": "GetVersionExA", "args": [2147417308], "addr_func": "5242980", "addr": 4572391, "ret": "<BV32 retval_GetVersionExA_360501_32>"}, {"name": "GetEnvironmentVariableA", "args": ["__MSVCRT_HEAP_SELECT", 2147412808, 4240], "addr_func": "5242976", "addr": 4572444, "ret": "<BV32 retval_GetEnvironmentVariableA_360503_32>"}, {"name": "GetModuleFileNameA", "args": [0, "3cb2fd26e550c2210a94d899a48ecd53216457e9c33f4a623bb3bb63263062a8.exe", 260], "addr_func": "5242916", "addr": 4572540, "ret": 68}, {"name": "GetModuleHandleA", "args": [0], "addr_func": "5242884", "addr": 4572325, "ret": 4194304}, {"name": "HeapAlloc", "args": [1, 0, 320], "addr_func": "5243032", "addr": 4577948, "ret": 3221258256}, {"name": "InitializeCriticalSection", "args": [4585992], "addr_func": "5243008", "addr": 4573657, "ret": "None"}, {"name": "InitializeCriticalSection", "args": [4586040], "addr_func": "5243008", "addr": 4573665, "ret": "None"}, {"name": "InitializeCriticalSection", "args": [4586016], "addr_func": "5243008", "addr": 4573673, "ret": "None"}, {"name": "InitializeCriticalSection", "args": [4585968], "addr_func": "5243008", "addr": 4573681, "ret": "None"}, {"name": "TlsAlloc", "args": [], "addr_func": "5242960", "addr": 4572115, "ret": 0}, {"name": "EnterCriticalSection", "args": [4586016], "addr_func": "5243012", "addr": 4573773, "ret": "None"}, {"name": "HeapAlloc", "args": [1, 8, 16836], "addr_func": "5243032", "addr": 4579728, "ret": 3221258584}, {"name": "VirtualAlloc", "args": [0, 1048576, 8192, 4], "addr_func": "5243036", "addr": 4579754, "ret": 3758096384}, {"name": "VirtualAlloc", "args": [3758096384, 32768, 4096, 4], "addr_func": "5243036", "addr": 4579894, "ret": 3758096384}, {"name": "LeaveCriticalSection", "args": [4586016], "addr_func": "5243016", "addr": 4573795, "ret": "None"}, {"name": "UserHook", "args": [], "addr_func": "4583057", "addr": 4576853, "ret": 0}, {"name": "TlsSetValue", "args": [1, 3758100352], "addr_func": "5242956", "addr": 4572155, "ret": 1}, {"name": "GetCurrentThreadId", "args": [], "addr_func": "5242952", "addr": 4572172, "ret": 0}, {"name": "HeapAlloc", "args": [1, 0, 1152], "addr_func": "5243032", "addr": 4575653, "ret": 3221275432}, {"name": "GetStartupInfoA", "args": [2147417396], "addr_func": "5242888", "addr": 4571759, "ret": "None"}, {"name": "GetStdHandle", "args": [4294967286], "addr_func": "5242944", "addr": 4572029, "ret": 1000}, {"name": "GetFileType", "args": [1000], "addr_func": "5242948", "addr": 4572043, "ret": "<BV32 retval_GetFileType_360505_32>"}, {"name": "GetStdHandle", "args": [4294967285], "addr_func": "5242944", "addr": 4572029, "ret": 1001}, {"name": "GetFileType", "args": [1001], "addr_func": "5242948", "addr": 4572043, "ret": "<BV32 retval_GetFileType_360507_32>"}, {"name": "GetStdHandle", "args": [4294967284], "addr_func": "5242944", "addr": 4572029, "ret": 1002}, {"name": "GetFileType", "args": [1002], "addr_func": "5242948", "addr": 4572043, "ret": "<BV32 retval_GetFileType_360517_32>"}, {"name": "SetHandleCount", "args": [32], "addr_func": "5242940", "addr": 4572098, "ret": "<BV32 retval_SetHandleCount_360518_32>"}, {"name": "GetCommandLineA", "args": [], "addr_func": "5242892", "addr": 4569630, "ret": 0}, {"name": "GetEnvironmentStringsW", "args": [], "addr_func": "5242936", "addr": 4571386, "ret": 0}, {"name": "WideCharToMultiByte", "args": [0, 0, 3221225480, 20, 0, 0, 0, 0], "addr_func": "5242928", "addr": 4571506, "ret": 16}, {"name": "EnterCriticalSection", "args": [4586016], "addr_func": "5243012", "addr": 4573773, "ret": "None"}, {"name": "LeaveCriticalSection", "args": [4586016], "addr_func": "5243016", "addr": 4573795, "ret": "None"}, {"name": "WideCharToMultiByte", "args": [0, 0, 3221225480, 20, "", 16, 0, 0], "addr_func": "5242928", "addr": 4571540, "ret": 16}, {"name": "FreeEnvironmentStringsW", "args": [3221225480], "addr_func": "5242924", "addr": 4571565, "ret": "<BV32 retval_FreeEnvironmentStringsW_360520_32>"}, {"name": "EnterCriticalSection", "args": [4586016], "addr_func": "5243012", "addr": 4573773, "ret": "None"}, {"name": "LeaveCriticalSection", "args": [4586016], "addr_func": "5243016", "addr": 4573795, "ret": "None"}, {"name": "EnterCriticalSection", "args": [4585992], "addr_func": "5243012", "addr": 4573773, "ret": "None"}, {"name": "InitializeCriticalSection", "args": [3758100288], "addr_func": "5243008", "addr": 4573746, "ret": "None"}, {"name": "LeaveCriticalSection", "args": [4585992], "addr_func": "5243016", "addr": 4573795, "ret": "None"}, {"name": "EnterCriticalSection", "args": [3758100288], "addr_func": "5243012", "addr": 4573773, "ret": "None"}, {"name": "GetACP", "args": [], "addr_func": "5243024", "addr": 4573888, "ret": 0}, {"name": "GetCPInfo", "args": [1252, 2147417408], "addr_func": "5243020", "addr": 4573950, "ret": "<BV32 retval_GetCPInfo_360521_32>"}, {"name": "UserHook", "args": [], "addr_func": "4574434", "addr": 4574265, "ret": 0}, {"name": "GetCPInfo", "args": [0, 2147417368], "addr_func": "5243020", "addr": 4574484, "ret": "<BV32 retval_GetCPInfo_360522_32>"}, {"name": "LeaveCriticalSection", "args": [3758100288], "addr_func": "5243016", "addr": 4573795, "ret": "None"}, {"name": "GetModuleFileNameA", "args": [0, "3cb2fd26e550c2210a94d899a48ecd53216457e9c33f4a623bb3bb63263062a8.exe", 260], "addr_func": "5242916", "addr": 4570805, "ret": 68}, {"name": "EnterCriticalSection", "args": [4586016], "addr_func": "5243012", "addr": 4573773, "ret": "None"}, {"name": "LeaveCriticalSection", "args": [4586016], "addr_func": "5243016", "addr": 4573795, "ret": "None"}, {"name": "EnterCriticalSection", "args": [4586016], "addr_func": "5243012", "addr": 4573773, "ret": "None"}, {"name": "LeaveCriticalSection", "args": [4586016], "addr_func": "5243016", "addr": 4573795, "ret": "None"}, {"name": "EnterCriticalSection", "args": [4586016], "addr_func": "5243012", "addr": 4573773, "ret": "None"}, {"name": "LeaveCriticalSection", "args": [4586016], "addr_func": "5243016", "addr": 4573795, "ret": "None"}, {"name": "GetStartupInfoA", "args": [2147417500], "addr_func": "5242888", "addr": 4569673, "ret": "None"}, {"name": "GetModuleHandleA", "args": [0], "addr_func": "5242884", "addr": 4569708, "ret": 4194304}]}, "sections": {".data": {"vaddr": 4198400, "memsize": 390165, "is_readable": true, "is_writable": true, "is_executable": false}, ".rsrc": {"vaddr": 4591616, "memsize": 13968, "is_readable": true, "is_writable": false, "is_executable": false}}}