{"0": {"status": "errored", "trace": [{"name": "main", "args": ["bb472659fae10a9d6b5396aa6bd416183a5b389ffcd0c98e90e47010a7be6f60.exe"], "addr": 4659064, "ret": "symbolic", "addr_func": 4659064}]}, "sections": {"CODE": {"vaddr": 4198400, "memsize": 460780, "is_readable": true, "is_writable": false, "is_executable": true}, "DATA": {"vaddr": 4661248, "memsize": 40136, "is_readable": true, "is_writable": true, "is_executable": false}, "BSS": {"vaddr": 4702208, "memsize": 3301, "is_readable": true, "is_writable": true, "is_executable": false}, ".idata": {"vaddr": 4706304, "memsize": 8864, "is_readable": true, "is_writable": true, "is_executable": false}, ".tls": {"vaddr": 4718592, "memsize": 16, "is_readable": true, "is_writable": true, "is_executable": false}, ".rdata": {"vaddr": 4722688, "memsize": 24, "is_readable": true, "is_writable": false, "is_executable": false}, ".reloc": {"vaddr": 4726784, "memsize": 33788, "is_readable": true, "is_writable": false, "is_executable": false}, ".rsrc": {"vaddr": 4763648, "memsize": 229132, "is_readable": true, "is_writable": false, "is_executable": false}}}