{"0": {"status": "active", "trace": [{"name": "main", "args": ["mirai408"], "addr": 134512996, "ret": "symbolic", "addr_func": 134512996}, {"name": "unlink", "ref_str": {"1": 2147418060}, "args": ["mirai408"], "addr_func": "137363466", "addr": 134538725, "ret": 0}, {"name": "rt_sigprocmask", "args": [0, 2147417356, 0, 8], "addr_func": "137363631", "addr": 134538762, "ret": 0}, {"name": "rt_sigaction", "args": [17, 2147415672], "addr_func": "137363630", "addr": 134556290, "ret": 0}, {"name": "rt_sigaction", "args": [5, 2147415672], "addr_func": "137363630", "addr": 134556290, "ret": 0}, {"name": "open", "ref_str": {"1": 134558446}, "args": ["/dev/watchdog", 2, 0], "addr_func": "137363461", "addr": 134538801, "ret": 3}, {"name": "ioctl", "ref_str": {"3": 2147417772}, "args": [3, 2147768068, "\u0001"], "addr_func": "137363510", "addr": 134538846, "ret": "<BV32 unconstrained_ret_ioctl_584650_32{UNINITIALIZED}>"}, {"name": "close", "args": [3], "addr_func": "137363462", "addr": 134538854, "ret": 0}, {"name": "chdir", "ref_str": {"1": 134558317}, "args": ["/"], "addr_func": "137363468", "addr": 134538875, "ret": 0}, {"name": "socket", "args": [2, 2, 0], "addr_func": "137363558", "addr": 134549367, "ret": 3}, {"name": "connect", "args": [3, 2147416112, 16], "addr_func": "137363558", "addr": 134548892, "ret": 0}, {"name": "getsockname", "args": [3, 2147416112, 2147416128], "addr_func": "137363558", "addr": 134548935, "ret": 0}, {"name": "close", "args": [3], "addr_func": "137363462", "addr": 134546582, "ret": 0}]}, "sections": {"": {"vaddr": 0, "memsize": 0, "is_readable": true, "is_writable": false, "is_executable": false}, ".init": {"vaddr": 134512788, "memsize": 28, "is_readable": true, "is_writable": false, "is_executable": true}, ".text": {"vaddr": 134512816, "memsize": 45462, "is_readable": true, "is_writable": false, "is_executable": true}, ".fini": {"vaddr": 134558278, "memsize": 23, "is_readable": true, "is_writable": false, "is_executable": true}, ".rodata": {"vaddr": 134558304, "memsize": 3008, "is_readable": true, "is_writable": false, "is_executable": false}, ".ctors": {"vaddr": 134561792, "memsize": 8, "is_readable": true, "is_writable": true, "is_executable": false}, ".dtors": {"vaddr": 134561800, "memsize": 8, "is_readable": true, "is_writable": true, "is_executable": false}, ".data": {"vaddr": 134561824, "memsize": 108, "is_readable": true, "is_writable": true, "is_executable": false}, ".bss": {"vaddr": 134561952, "memsize": 1632, "is_readable": true, "is_writable": true, "is_executable": false}, ".shstrtab": {"vaddr": 0, "memsize": 62, "is_readable": true, "is_writable": false, "is_executable": false}}}