[{"0": {"status": "active", "trace": [{"name": "main", "args": ["d071005da43784dc89b13b35a9a26a78a18c636bdc169e76541d0502dd81bf1b.exe"], "addr": 4299520, "ret": "symbolic", "addr_func": 4299520}]}, "sections": {".edlwv": {"vaddr": 4198400, "memsize": 69632, "is_readable": true, "is_writable": true, "is_executable": true}, "UPX1": {"vaddr": 4268032, "memsize": 36864, "is_readable": true, "is_writable": true, "is_executable": true}, ".oh": {"vaddr": 4304896, "memsize": 4096, "is_readable": true, "is_writable": true, "is_executable": false}}}]